
[
  {
    "$type": "ModListMetadata, Wabbajack.Lib",
    "title": "Skyrim KIRBYKINGS NSFW Edition Modlist",
    "description": "The Next Generation of Skyrim Immersive Adult Adventure with Graphic Overhauls.",
    "author": "Kimutkirby",
    "maintainers": [
      "github/kimut-kirby"
    ],
    "game": "skyrimspecialedition",
    "tags": [
      "NSFW",
      "Steam",
      "Total Overhaul"
    ],
    "nsfw": true,
    "image_contains_title": false,
    "force_down": false,
    "links": {
      "$type": "Links, Wabbajack.Lib",
      "image": "https://raw.githubusercontent.com/kimutkirby/Skyrim-KIRBYKINGS-NSFW-Edition/refs/heads/main/Kirbykings%20NSFW%20WEBPs.webp",
      "readme": "https://github.com/kimutkirby/Skyrim-KIRBYKINGS-NSFW-Edition/blob/main/README.md",
      "download": "https://authored-files.wabbajack.org/Skyrim%20Kirbykings%20NSFW%20Modlist.wabbajack_3047ece9-04a2-4594-b8c9-3e8d4dbc7d33",
      "machineURL": "SkyrimKIRBYKINGSNSFWEditionModlist",
      "discordURL": "https://discord.com/invite/4N4rWBFVKP"
    },
    "download_metadata": {
      "$type": "DownloadMetadata, Wabbajack.Lib",
      "Hash": "yaKN0jA594M=",
      "Size": 557478271,
      "NumberOfArchives": 2639,
      "SizeOfArchives": 245962785745,
      "NumberOfInstalledFiles": 465677,
      "SizeOfInstalledFiles": 412204584200
    },
    "version": "2.3.0"
  }
]
